ipydfconfig/__init__.py
ipydfconfig-0.1.2.dist-info/licenses/LICENSE
ipydfconfig-0.1.2.dist-info/METADATA
ipydfconfig-0.1.2.dist-info/WHEEL
ipydfconfig-0.1.2.dist-info/top_level.txt
ipydfconfig-0.1.2.dist-info/RECORD
