Metadata-Version: 2.4
Name: ipydfconfig
Version: 0.1.2
Author-email: David Koop <dakoop@niu.edu>
License-Expression: BSD-3-Clause
Project-URL: Homepage, https://github.com/dakoop/ipydfconfig
Classifier: Programming Language :: Python :: 3
Classifier: Operating System :: OS Independent
License-File: LICENSE
Requires-Dist: ipython
Dynamic: license-file
